[
    {
        "span": 5.0,
        "node": "A",
        "treatment": 1.0,
        "field_number": 5001.0,
        "sensor_model": "TDR-315N",
        "Depth": 6.0,
        "SDI-12 Address": "1",
        "Analog address": null,
        "sensor_id": "5001A1TDR0623",
        "Serial Number": "15011637",
        "Status": null,
        "m": null,
        "Unnamed: 12": null,
        "Unnamed: 13": null,
        "b": null,
        "Unnamed: 15": null,
        "Unnamed: 16": null
    },
    {
        "span": 5.0,
        "node": "A",
        "treatment": 1.0,
        "field_number": 5001.0,
        "sensor_model": "TDR-315N",
        "Depth": 18.0,
        "SDI-12 Address": "2",
        "Analog address": null,
        "sensor_id": "5001A1TDR1823",
        "Serial Number": "15011684",
        "Status": null,
        "m": null,
        "Unnamed: 12": null,
        "Unnamed: 13": null,
        "b": null,
        "Unnamed: 15": null,
        "Unnamed: 16": null
    },
    {
        "span": 5.0,
        "node": "A",
        "treatment": 1.0,
        "field_number": 5001.0,
        "sensor_model": "TDR-315N",
        "Depth": 30.0,
        "SDI-12 Address": "3",
        "Analog address": null,
        "sensor_id": "5001A1TDR3023",
        "Serial Number": "15011635",
        "Status": null,
        "m": null,
        "Unnamed: 12": null,
        "Unnamed: 13": null,
        "b": null,
        "Unnamed: 15": null,
        "Unnamed: 16": null
    },
    {
        "span": 5.0,
        "node": "A",
        "treatment": 1.0,
        "field_number": 5001.0,
        "sensor_model": "TDR-315N",
        "Depth": 42.0,
        "SDI-12 Address": "4",
        "Analog address": null,
        "sensor_id": "5001A1TDR4223",
        "Serial Number": "15011642",
        "Status": null,
        "m": null,
        "Unnamed: 12": null,
        "Unnamed: 13": null,
        "b": null,
        "Unnamed: 15": null,
        "Unnamed: 16": null
    },
    {
        "span": 5.0,
        "node": "A",
        "treatment": 1.0,
        "field_number": 5001.0,
        "sensor_model": "200SS",
        "Depth": 6.0,
        "SDI-12 Address": null,
        "Analog address": 1.0,
        "sensor_id": "5001A1WAM0623",
        "Serial Number": null,
        "Status": null,
        "m": null,
        "Unnamed: 12": null,
        "Unnamed: 13": null,
        "b": null,
        "Unnamed: 15": null,
        "Unnamed: 16": null
    },
    {
        "span": 5.0,
        "node": "A",
        "treatment": 1.0,
        "field_number": 5001.0,
        "sensor_model": "200SS",
        "Depth": 18.0,
        "SDI-12 Address": null,
        "Analog address": 2.0,
        "sensor_id": "5001A1WAM1823",
        "Serial Number": null,
        "Status": null,
        "m": null,
        "Unnamed: 12": null,
        "Unnamed: 13": null,
        "b": null,
        "Unnamed: 15": null,
        "Unnamed: 16": null
    },
    {
        "span": 5.0,
        "node": "A",
        "treatment": 1.0,
        "field_number": 5001.0,
        "sensor_model": "200SS",
        "Depth": 30.0,
        "SDI-12 Address": null,
        "Analog address": 3.0,
        "sensor_id": "5001A1WAM3023",
        "Serial Number": null,
        "Status": null,
        "m": null,
        "Unnamed: 12": null,
        "Unnamed: 13": null,
        "b": null,
        "Unnamed: 15": null,
        "Unnamed: 16": null
    },
    {
        "span": 5.0,
        "node": "A",
        "treatment": 1.0,
        "field_number": 5001.0,
        "sensor_model": "200SS",
        "Depth": 42.0,
        "SDI-12 Address": null,
        "Analog address": 4.0,
        "sensor_id": "5001A1WAM4223",
        "Serial Number": null,
        "Status": null,
        "m": null,
        "Unnamed: 12": null,
        "Unnamed: 13": null,
        "b": null,
        "Unnamed: 15": null,
        "Unnamed: 16": null
    },
    {
        "span": 5.0,
        "node": "A",
        "treatment": 2.0,
        "field_number": 5003.0,
        "sensor_model": "SI-4H1_SS_8862",
        "Depth": null,
        "SDI-12 Address": "6",
        "Analog address": null,
        "sensor_id": "5003A2IRTXX23",
        "Serial Number": "B078864",
        "Status": "broken",
        "m": "107961",
        "Unnamed: 12": "11937966",
        "Unnamed: 13": "1990875783",
        "b": "4305",
        "Unnamed: 15": "88135",
        "Unnamed: 16": "476785"
    },
    {
        "span": 5.0,
        "node": "B",
        "treatment": 1.0,
        "field_number": 5009.0,
        "sensor_model": "SI-4H1_SS_8862",
        "Depth": null,
        "SDI-12 Address": "j",
        "Analog address": null,
        "sensor_id": "5009B1IRTXX23",
        "Serial Number": "B078872",
        "Status": null,
        "m": null,
        "Unnamed: 12": null,
        "Unnamed: 13": null,
        "b": null,
        "Unnamed: 15": null,
        "Unnamed: 16": null
    },
    {
        "span": 5.0,
        "node": "B",
        "treatment": 1.0,
        "field_number": 5009.0,
        "sensor_model": "TDR-315N",
        "Depth": 6.0,
        "SDI-12 Address": "f",
        "Analog address": null,
        "sensor_id": "5009B1TDR0623",
        "Serial Number": "15011626",
        "Status": null,
        "m": null,
        "Unnamed: 12": null,
        "Unnamed: 13": null,
        "b": null,
        "Unnamed: 15": null,
        "Unnamed: 16": null
    },
    {
        "span": 5.0,
        "node": "B",
        "treatment": 1.0,
        "field_number": 5009.0,
        "sensor_model": "TDR-315N",
        "Depth": 18.0,
        "SDI-12 Address": "g",
        "Analog address": null,
        "sensor_id": "5009B1TDR1823",
        "Serial Number": "15011624",
        "Status": null,
        "m": null,
        "Unnamed: 12": null,
        "Unnamed: 13": null,
        "b": null,
        "Unnamed: 15": null,
        "Unnamed: 16": null
    },
    {
        "span": 5.0,
        "node": "B",
        "treatment": 1.0,
        "field_number": 5009.0,
        "sensor_model": "TDR-315N",
        "Depth": 30.0,
        "SDI-12 Address": "h",
        "Analog address": null,
        "sensor_id": "5009B1TDR3023",
        "Serial Number": "15011644",
        "Status": null,
        "m": null,
        "Unnamed: 12": null,
        "Unnamed: 13": null,
        "b": null,
        "Unnamed: 15": null,
        "Unnamed: 16": null
    },
    {
        "span": 5.0,
        "node": "B",
        "treatment": 1.0,
        "field_number": 5009.0,
        "sensor_model": "TDR-315N",
        "Depth": 42.0,
        "SDI-12 Address": "i",
        "Analog address": null,
        "sensor_id": "5009B1TDR4223",
        "Serial Number": "15011639",
        "Status": null,
        "m": null,
        "Unnamed: 12": null,
        "Unnamed: 13": null,
        "b": null,
        "Unnamed: 15": null,
        "Unnamed: 16": null
    },
    {
        "span": 5.0,
        "node": "B",
        "treatment": 1.0,
        "field_number": 5009.0,
        "sensor_model": "200SS",
        "Depth": 6.0,
        "SDI-12 Address": null,
        "Analog address": 1.0,
        "sensor_id": "5009B1WAM0623",
        "Serial Number": null,
        "Status": null,
        "m": null,
        "Unnamed: 12": null,
        "Unnamed: 13": null,
        "b": null,
        "Unnamed: 15": null,
        "Unnamed: 16": null
    },
    {
        "span": 5.0,
        "node": "B",
        "treatment": 1.0,
        "field_number": 5009.0,
        "sensor_model": "200SS",
        "Depth": 18.0,
        "SDI-12 Address": null,
        "Analog address": 2.0,
        "sensor_id": "5009B1WAM1823",
        "Serial Number": null,
        "Status": null,
        "m": null,
        "Unnamed: 12": null,
        "Unnamed: 13": null,
        "b": null,
        "Unnamed: 15": null,
        "Unnamed: 16": null
    },
    {
        "span": 5.0,
        "node": "B",
        "treatment": 1.0,
        "field_number": 5009.0,
        "sensor_model": "200SS",
        "Depth": 30.0,
        "SDI-12 Address": null,
        "Analog address": 3.0,
        "sensor_id": "5009B1WAM3023",
        "Serial Number": null,
        "Status": null,
        "m": null,
        "Unnamed: 12": null,
        "Unnamed: 13": null,
        "b": null,
        "Unnamed: 15": null,
        "Unnamed: 16": null
    },
    {
        "span": 5.0,
        "node": "B",
        "treatment": 1.0,
        "field_number": 5009.0,
        "sensor_model": "200SS",
        "Depth": 42.0,
        "SDI-12 Address": null,
        "Analog address": 4.0,
        "sensor_id": "5009B1WAM4223",
        "Serial Number": null,
        "Status": null,
        "m": null,
        "Unnamed: 12": null,
        "Unnamed: 13": null,
        "b": null,
        "Unnamed: 15": null,
        "Unnamed: 16": null
    },
    {
        "span": 5.0,
        "node": "B",
        "treatment": 5.0,
        "field_number": 5005.0,
        "sensor_model": "SI-4H1_SS_8862",
        "Depth": null,
        "SDI-12 Address": "a",
        "Analog address": null,
        "sensor_id": "5005B5IRTXX23",
        "Serial Number": "B078875",
        "Status": null,
        "m": "89895",
        "Unnamed: 12": "11426143",
        "Unnamed: 13": "1900824923",
        "b": "3383",
        "Unnamed: 15": "67613",
        "Unnamed: 16": "-5065908"
    },
    {
        "span": 5.0,
        "node": "B",
        "treatment": 5.0,
        "field_number": 5005.0,
        "sensor_model": "TDR-315N",
        "Depth": 6.0,
        "SDI-12 Address": "7",
        "Analog address": null,
        "sensor_id": "5005B5TDR0623",
        "Serial Number": "15011634",
        "Status": null,
        "m": null,
        "Unnamed: 12": null,
        "Unnamed: 13": null,
        "b": null,
        "Unnamed: 15": null,
        "Unnamed: 16": null
    },
    {
        "span": 5.0,
        "node": "B",
        "treatment": 5.0,
        "field_number": 5005.0,
        "sensor_model": "TDR-315N",
        "Depth": 18.0,
        "SDI-12 Address": "8",
        "Analog address": null,
        "sensor_id": "5005B5TDR1823",
        "Serial Number": "15011674",
        "Status": null,
        "m": null,
        "Unnamed: 12": null,
        "Unnamed: 13": null,
        "b": null,
        "Unnamed: 15": null,
        "Unnamed: 16": null
    },
    {
        "span": 5.0,
        "node": "B",
        "treatment": 5.0,
        "field_number": 5005.0,
        "sensor_model": "TDR-315N",
        "Depth": 30.0,
        "SDI-12 Address": "9",
        "Analog address": null,
        "sensor_id": "5005B5TDR3023",
        "Serial Number": "15011655",
        "Status": null,
        "m": null,
        "Unnamed: 12": null,
        "Unnamed: 13": null,
        "b": null,
        "Unnamed: 15": null,
        "Unnamed: 16": null
    },
    {
        "span": 5.0,
        "node": "B",
        "treatment": 5.0,
        "field_number": 5005.0,
        "sensor_model": "200SS",
        "Depth": 6.0,
        "SDI-12 Address": null,
        "Analog address": 5.0,
        "sensor_id": "5005B5WAM0623",
        "Serial Number": null,
        "Status": null,
        "m": null,
        "Unnamed: 12": null,
        "Unnamed: 13": null,
        "b": null,
        "Unnamed: 15": null,
        "Unnamed: 16": null
    },
    {
        "span": 5.0,
        "node": "B",
        "treatment": 5.0,
        "field_number": 5005.0,
        "sensor_model": "200SS",
        "Depth": 18.0,
        "SDI-12 Address": null,
        "Analog address": 6.0,
        "sensor_id": "5005B5WAM1823",
        "Serial Number": null,
        "Status": null,
        "m": null,
        "Unnamed: 12": null,
        "Unnamed: 13": null,
        "b": null,
        "Unnamed: 15": null,
        "Unnamed: 16": null
    },
    {
        "span": 5.0,
        "node": "B",
        "treatment": 5.0,
        "field_number": 5005.0,
        "sensor_model": "200SS",
        "Depth": 30.0,
        "SDI-12 Address": null,
        "Analog address": 7.0,
        "sensor_id": "5005B5WAM3023",
        "Serial Number": null,
        "Status": null,
        "m": null,
        "Unnamed: 12": null,
        "Unnamed: 13": null,
        "b": null,
        "Unnamed: 15": null,
        "Unnamed: 16": null
    },
    {
        "span": 5.0,
        "node": "B",
        "treatment": 5.0,
        "field_number": 5005.0,
        "sensor_model": "200SS",
        "Depth": 42.0,
        "SDI-12 Address": null,
        "Analog address": 8.0,
        "sensor_id": "5005B5WAM4223",
        "Serial Number": null,
        "Status": null,
        "m": null,
        "Unnamed: 12": null,
        "Unnamed: 13": null,
        "b": null,
        "Unnamed: 15": null,
        "Unnamed: 16": null
    },
    {
        "span": 5.0,
        "node": "B",
        "treatment": 5.0,
        "field_number": 5010.0,
        "sensor_model": "SI-4H1_SS_8862",
        "Depth": null,
        "SDI-12 Address": "e",
        "Analog address": null,
        "sensor_id": "5010B5IRTXX23",
        "Serial Number": "B078868",
        "Status": null,
        "m": "109763",
        "Unnamed: 12": "12710835",
        "Unnamed: 13": "2052249537",
        "b": "5504",
        "Unnamed: 15": "81183",
        "Unnamed: 16": "570407"
    },
    {
        "span": 5.0,
        "node": "B",
        "treatment": 5.0,
        "field_number": 5010.0,
        "sensor_model": "TDR-315N",
        "Depth": 6.0,
        "SDI-12 Address": "b",
        "Analog address": null,
        "sensor_id": "5010B5TDR0623",
        "Serial Number": "15011650",
        "Status": null,
        "m": null,
        "Unnamed: 12": null,
        "Unnamed: 13": null,
        "b": null,
        "Unnamed: 15": null,
        "Unnamed: 16": null
    },
    {
        "span": 5.0,
        "node": "B",
        "treatment": 5.0,
        "field_number": 5010.0,
        "sensor_model": "TDR-315N",
        "Depth": 18.0,
        "SDI-12 Address": "c",
        "Analog address": null,
        "sensor_id": "5010B5TDR1823",
        "Serial Number": "15011645",
        "Status": null,
        "m": null,
        "Unnamed: 12": null,
        "Unnamed: 13": null,
        "b": null,
        "Unnamed: 15": null,
        "Unnamed: 16": null
    },
    {
        "span": 5.0,
        "node": "B",
        "treatment": 5.0,
        "field_number": 5010.0,
        "sensor_model": "TDR-315N",
        "Depth": 30.0,
        "SDI-12 Address": "d",
        "Analog address": null,
        "sensor_id": "5010B5TDR3023",
        "Serial Number": "15011638",
        "Status": null,
        "m": null,
        "Unnamed: 12": null,
        "Unnamed: 13": null,
        "b": null,
        "Unnamed: 15": null,
        "Unnamed: 16": null
    },
    {
        "span": 5.0,
        "node": "B",
        "treatment": 5.0,
        "field_number": 5010.0,
        "sensor_model": "200SS",
        "Depth": 6.0,
        "SDI-12 Address": null,
        "Analog address": 9.0,
        "sensor_id": "5010B5WAM0623",
        "Serial Number": null,
        "Status": null,
        "m": null,
        "Unnamed: 12": null,
        "Unnamed: 13": null,
        "b": null,
        "Unnamed: 15": null,
        "Unnamed: 16": null
    },
    {
        "span": 5.0,
        "node": "B",
        "treatment": 5.0,
        "field_number": 5010.0,
        "sensor_model": "200SS",
        "Depth": 18.0,
        "SDI-12 Address": null,
        "Analog address": 10.0,
        "sensor_id": "5010B5WAM1823",
        "Serial Number": null,
        "Status": null,
        "m": null,
        "Unnamed: 12": null,
        "Unnamed: 13": null,
        "b": null,
        "Unnamed: 15": null,
        "Unnamed: 16": null
    },
    {
        "span": 5.0,
        "node": "B",
        "treatment": 5.0,
        "field_number": 5010.0,
        "sensor_model": "200SS",
        "Depth": 30.0,
        "SDI-12 Address": null,
        "Analog address": 11.0,
        "sensor_id": "5010B5WAM3023",
        "Serial Number": null,
        "Status": null,
        "m": null,
        "Unnamed: 12": null,
        "Unnamed: 13": null,
        "b": null,
        "Unnamed: 15": null,
        "Unnamed: 16": null
    },
    {
        "span": 5.0,
        "node": "B",
        "treatment": 5.0,
        "field_number": 5010.0,
        "sensor_model": "200SS",
        "Depth": 42.0,
        "SDI-12 Address": null,
        "Analog address": 12.0,
        "sensor_id": "5010B5WAM4223",
        "Serial Number": null,
        "Status": null,
        "m": null,
        "Unnamed: 12": null,
        "Unnamed: 13": null,
        "b": null,
        "Unnamed: 15": null,
        "Unnamed: 16": null
    },
    {
        "span": 5.0,
        "node": "C",
        "treatment": 5.0,
        "field_number": 5013.0,
        "sensor_model": "SI-4H1_SS_8862",
        "Depth": null,
        "SDI-12 Address": "o",
        "Analog address": null,
        "sensor_id": "5013C5IRTXX23",
        "Serial Number": "B078861",
        "Status": null,
        "m": "109674",
        "Unnamed: 12": "12254467",
        "Unnamed: 13": "2013077902",
        "b": "3993",
        "Unnamed: 15": "166717",
        "Unnamed: 16": "-2636157"
    },
    {
        "span": 5.0,
        "node": "C",
        "treatment": 5.0,
        "field_number": 5013.0,
        "sensor_model": "TDR-315N",
        "Depth": 6.0,
        "SDI-12 Address": "l",
        "Analog address": null,
        "sensor_id": "5013C5TDR0623",
        "Serial Number": "15011628",
        "Status": null,
        "m": null,
        "Unnamed: 12": null,
        "Unnamed: 13": null,
        "b": null,
        "Unnamed: 15": null,
        "Unnamed: 16": null
    },
    {
        "span": 5.0,
        "node": "C",
        "treatment": 5.0,
        "field_number": 5013.0,
        "sensor_model": "TDR-315N",
        "Depth": 18.0,
        "SDI-12 Address": "m",
        "Analog address": null,
        "sensor_id": "5013C5TDR1823",
        "Serial Number": "15011641",
        "Status": null,
        "m": null,
        "Unnamed: 12": null,
        "Unnamed: 13": null,
        "b": null,
        "Unnamed: 15": null,
        "Unnamed: 16": null
    },
    {
        "span": 5.0,
        "node": "C",
        "treatment": 5.0,
        "field_number": 5013.0,
        "sensor_model": "TDR-315N",
        "Depth": 30.0,
        "SDI-12 Address": "n",
        "Analog address": null,
        "sensor_id": "5013C5TDR3023",
        "Serial Number": "15011680",
        "Status": null,
        "m": null,
        "Unnamed: 12": null,
        "Unnamed: 13": null,
        "b": null,
        "Unnamed: 15": null,
        "Unnamed: 16": null
    },
    {
        "span": 5.0,
        "node": "C",
        "treatment": 5.0,
        "field_number": 5013.0,
        "sensor_model": "200SS",
        "Depth": 6.0,
        "SDI-12 Address": null,
        "Analog address": null,
        "sensor_id": "5013B5WAM0623",
        "Serial Number": null,
        "Status": null,
        "m": null,
        "Unnamed: 12": null,
        "Unnamed: 13": null,
        "b": null,
        "Unnamed: 15": null,
        "Unnamed: 16": null
    },
    {
        "span": 5.0,
        "node": "C",
        "treatment": 5.0,
        "field_number": 5013.0,
        "sensor_model": "200SS",
        "Depth": 18.0,
        "SDI-12 Address": null,
        "Analog address": null,
        "sensor_id": "5013B5WAM1823",
        "Serial Number": null,
        "Status": null,
        "m": null,
        "Unnamed: 12": null,
        "Unnamed: 13": null,
        "b": null,
        "Unnamed: 15": null,
        "Unnamed: 16": null
    },
    {
        "span": 5.0,
        "node": "C",
        "treatment": 5.0,
        "field_number": 5013.0,
        "sensor_model": "200SS",
        "Depth": 30.0,
        "SDI-12 Address": null,
        "Analog address": null,
        "sensor_id": "5013B5WAM3023",
        "Serial Number": null,
        "Status": null,
        "m": null,
        "Unnamed: 12": null,
        "Unnamed: 13": null,
        "b": null,
        "Unnamed: 15": null,
        "Unnamed: 16": null
    },
    {
        "span": 5.0,
        "node": "C",
        "treatment": 5.0,
        "field_number": 5013.0,
        "sensor_model": "200SS",
        "Depth": 42.0,
        "SDI-12 Address": null,
        "Analog address": null,
        "sensor_id": "5013B5WAM4223",
        "Serial Number": null,
        "Status": null,
        "m": null,
        "Unnamed: 12": null,
        "Unnamed: 13": null,
        "b": null,
        "Unnamed: 15": null,
        "Unnamed: 16": null
    },
    {
        "span": 5.0,
        "node": "C",
        "treatment": 1.0,
        "field_number": 5014.0,
        "sensor_model": "SI-4H1_SS_8862",
        "Depth": null,
        "SDI-12 Address": "t",
        "Analog address": null,
        "sensor_id": "5014C1IRTXX23",
        "Serial Number": "B078874",
        "Status": null,
        "m": "124835",
        "Unnamed: 12": "12214235",
        "Unnamed: 13": "1992102375",
        "b": "3799",
        "Unnamed: 15": "-10097",
        "Unnamed: 16": "1336669"
    },
    {
        "span": 5.0,
        "node": "C",
        "treatment": 1.0,
        "field_number": 5014.0,
        "sensor_model": "TDR-315N",
        "Depth": 6.0,
        "SDI-12 Address": "p",
        "Analog address": null,
        "sensor_id": "5014C1TDR0623",
        "Serial Number": "15011630",
        "Status": null,
        "m": null,
        "Unnamed: 12": null,
        "Unnamed: 13": null,
        "b": null,
        "Unnamed: 15": null,
        "Unnamed: 16": null
    },
    {
        "span": 5.0,
        "node": "C",
        "treatment": 1.0,
        "field_number": 5014.0,
        "sensor_model": "TDR-315N",
        "Depth": 18.0,
        "SDI-12 Address": "q",
        "Analog address": null,
        "sensor_id": "5014C1TDR1823",
        "Serial Number": "15011640",
        "Status": null,
        "m": null,
        "Unnamed: 12": null,
        "Unnamed: 13": null,
        "b": null,
        "Unnamed: 15": null,
        "Unnamed: 16": null
    },
    {
        "span": 5.0,
        "node": "C",
        "treatment": 1.0,
        "field_number": 5014.0,
        "sensor_model": "TDR-315N",
        "Depth": 30.0,
        "SDI-12 Address": "r",
        "Analog address": null,
        "sensor_id": "5014C1TDR3023",
        "Serial Number": "15011681",
        "Status": null,
        "m": null,
        "Unnamed: 12": null,
        "Unnamed: 13": null,
        "b": null,
        "Unnamed: 15": null,
        "Unnamed: 16": null
    },
    {
        "span": 5.0,
        "node": "C",
        "treatment": 1.0,
        "field_number": 5014.0,
        "sensor_model": "TDR-315N",
        "Depth": 42.0,
        "SDI-12 Address": "s",
        "Analog address": null,
        "sensor_id": "5014C1TDR4223",
        "Serial Number": "15011631",
        "Status": null,
        "m": null,
        "Unnamed: 12": null,
        "Unnamed: 13": null,
        "b": null,
        "Unnamed: 15": null,
        "Unnamed: 16": null
    },
    {
        "span": 5.0,
        "node": "C",
        "treatment": 1.0,
        "field_number": 5014.0,
        "sensor_model": "200SS",
        "Depth": 6.0,
        "SDI-12 Address": null,
        "Analog address": null,
        "sensor_id": "5014C1WAM0623",
        "Serial Number": null,
        "Status": null,
        "m": null,
        "Unnamed: 12": null,
        "Unnamed: 13": null,
        "b": null,
        "Unnamed: 15": null,
        "Unnamed: 16": null
    },
    {
        "span": 5.0,
        "node": "C",
        "treatment": 1.0,
        "field_number": 5014.0,
        "sensor_model": "200SS",
        "Depth": 18.0,
        "SDI-12 Address": null,
        "Analog address": null,
        "sensor_id": "5014C1WAM1823",
        "Serial Number": null,
        "Status": null,
        "m": null,
        "Unnamed: 12": null,
        "Unnamed: 13": null,
        "b": null,
        "Unnamed: 15": null,
        "Unnamed: 16": null
    },
    {
        "span": 5.0,
        "node": "C",
        "treatment": 1.0,
        "field_number": 5014.0,
        "sensor_model": "200SS",
        "Depth": 30.0,
        "SDI-12 Address": null,
        "Analog address": null,
        "sensor_id": "5014C1WAM3023",
        "Serial Number": null,
        "Status": null,
        "m": null,
        "Unnamed: 12": null,
        "Unnamed: 13": null,
        "b": null,
        "Unnamed: 15": null,
        "Unnamed: 16": null
    },
    {
        "span": 5.0,
        "node": "C",
        "treatment": 1.0,
        "field_number": 5014.0,
        "sensor_model": "200SS",
        "Depth": 42.0,
        "SDI-12 Address": null,
        "Analog address": null,
        "sensor_id": "5014C1WAM4223",
        "Serial Number": null,
        "Status": null,
        "m": null,
        "Unnamed: 12": null,
        "Unnamed: 13": null,
        "b": null,
        "Unnamed: 15": null,
        "Unnamed: 16": null
    },
    {
        "span": 5.0,
        "node": "C",
        "treatment": 2.0,
        "field_number": 5015.0,
        "sensor_model": "SI-4H1_SS_8862",
        "Depth": 40.0,
        "SDI-12 Address": "u",
        "Analog address": null,
        "sensor_id": "5015C2IRTXX23",
        "Serial Number": "B078878",
        "Status": null,
        "m": "111230",
        "Unnamed: 12": "12771827",
        "Unnamed: 13": "2074135734",
        "b": "4376",
        "Unnamed: 15": "-48573",
        "Unnamed: 16": "4617513"
    },
    {
        "span": 5.0,
        "node": "C",
        "treatment": 2.0,
        "field_number": null,
        "sensor_model": "SI-4H1_SS_8863",
        "Depth": null,
        "SDI-12 Address": "k",
        "Analog address": null,
        "sensor_id": "5006A2IRTXX23",
        "Serial Number": "B078865",
        "Status": null,
        "m": "110357",
        "Unnamed: 12": "12621703",
        "Unnamed: 13": "2078480792",
        "b": "-20191",
        "Unnamed: 15": "289489",
        "Unnamed: 16": "992624"
    }
]